{
  "version": "6",
  "dialect": "sqlite",
  "id": "f3b548d9-d455-4ddc-8ef7-8f2180f80a01",
  "prevId": "b7d5d091-46d8-45a3-8e5c-7884fe47763b",
  "tables": {
    "altwatcher_link": {
      "name": "altwatcher_link",
      "columns": {
        "id": {
          "name": "id",
          "type": "integer",
          "primaryKey": true,
          "notNull": true,
          "autoincrement": true
        },
        "title": {
          "name": "title",
          "type": "text",
          "primaryKey": false,
          "notNull": true,
          "autoincrement": false
        },
        "link": {
          "name": "link",
          "type": "text",
          "primaryKey": false,
          "notNull": true,
          "autoincrement": false
        },
        "description": {
          "name": "description",
          "type": "text",
          "primaryKey": false,
          "notNull": false,
          "autoincrement": false
        },
        "manga": {
          "name": "manga",
          "type": "integer",
          "primaryKey": false,
          "notNull": true,
          "autoincrement": false,
          "default": 0
        },
        "anime": {
          "name": "anime",
          "type": "integer",
          "primaryKey": false,
          "notNull": true,
          "autoincrement": false,
          "default": 0
        },
        "ranobe": {
          "name": "ranobe",
          "type": "integer",
          "primaryKey": false,
          "notNull": true,
          "autoincrement": false,
          "default": 0
        },
        "approved": {
          "name": "approved",
          "type": "integer",
          "primaryKey": false,
          "notNull": true,
          "autoincrement": false,
          "default": false
        },
        "number_of_downloads": {
          "name": "number_of_downloads",
          "type": "integer",
          "primaryKey": false,
          "notNull": true,
          "autoincrement": false,
          "default": 1
        },
        "is_default": {
          "name": "is_default",
          "type": "integer",
          "primaryKey": false,
          "notNull": true,
          "autoincrement": false,
          "default": false
        },
        "stable_id": {
          "name": "stable_id",
          "type": "text",
          "primaryKey": false,
          "notNull": false,
          "autoincrement": false
        }
      },
      "indexes": {
        "altwatcher_link_stable_id_unique": {
          "name": "altwatcher_link_stable_id_unique",
          "columns": [
            "stable_id"
          ],
          "isUnique": true
        }
      },
      "foreignKeys": {},
      "compositePrimaryKeys": {},
      "uniqueConstraints": {},
      "checkConstraints": {}
    }
  },
  "views": {},
  "enums": {},
  "_meta": {
    "schemas": {},
    "tables": {},
    "columns": {}
  },
  "internal": {
    "indexes": {}
  }
}